opencensus/__init__.py
opencensus/ext/__init__.py
opencensus/ext/httplib/__init__.py
opencensus/ext/httplib/trace.py
opencensus_ext_httplib-0.7.5.dist-info/METADATA
opencensus_ext_httplib-0.7.5.dist-info/WHEEL
opencensus_ext_httplib-0.7.5.dist-info/namespace_packages.txt
opencensus_ext_httplib-0.7.5.dist-info/top_level.txt
opencensus_ext_httplib-0.7.5.dist-info/RECORD
